orismos/__init__.py
orismos-0.0.1.dist-info/METADATA
orismos-0.0.1.dist-info/WHEEL
orismos-0.0.1.dist-info/top_level.txt
orismos-0.0.1.dist-info/RECORD
